pymed/__init__.py
pymed/api.py
pymed/article.py
pymed/book.py
pymed/helpers.py
pymed/version.py
pymed_iplweb-0.8.10.dist-info/AUTHORS.txt
pymed_iplweb-0.8.10.dist-info/LICENCE
pymed_iplweb-0.8.10.dist-info/METADATA
pymed_iplweb-0.8.10.dist-info/WHEEL
pymed_iplweb-0.8.10.dist-info/top_level.txt
pymed_iplweb-0.8.10.dist-info/RECORD
