Metadata-Version: 2.1
Name: pymed-iplweb
Version: 0.8.10
Summary: Python library for access to PubMed
Home-page: https://github.com/mpasternak/pymed-iplweb
Author: Gijs Wobben
Author-email: gijswobben@gmail.com
Maintainer: Michał Pasternak
Maintainer-email: michal.dtz@gmail.com
License: MIT
Keywords: PubMed PMC
Platform: UNKNOWN
Classifier: Topic :: Utilities
Classifier: Development Status :: 3 - Alpha
Classifier: Intended Audience :: Science/Research
Classifier: License :: OSI Approved :: MIT License
Classifier: Programming Language :: Python :: 3 :: Only
Requires-Dist: requests (>=2.20.0)
